[
  {
    "vault": "0x31515cfc4550d9c83e2d86e8a352886d1364e2d9",
    "winner": "0xb1b9dcb9f3a25e390fb37f597c2bf90b16889e41",
    "tier": 2,
    "prizeIndex": 15,
    "claimed": true,
    "amount": "3986613469521030589",
    "userTwab": "13306898638",
    "totalSupplyTwab": "463863593330"
  },
  {
    "vault": "0x31515cfc4550d9c83e2d86e8a352886d1364e2d9",
    "winner": "0xb1b9dcb9f3a25e390fb37f597c2bf90b16889e41",
    "tier": 3,
    "prizeIndex": 4,
    "claimed": false,
    "amount": "675696913715915538",
    "userTwab": "13306898638",
    "totalSupplyTwab": "463863593330"
  },
  {
    "vault": "0x31515cfc4550d9c83e2d86e8a352886d1364e2d9",
    "winner": "0xb1b9dcb9f3a25e390fb37f597c2bf90b16889e41",
    "tier": 3,
    "prizeIndex": 16,
    "claimed": false,
    "amount": "675696913715915538",
    "userTwab": "13306898638",
    "totalSupplyTwab": "463863593330"
  }
]