[
  {
    "vault": "0x80f5984ad748878c9822af1231deef7466ad85bf",
    "winner": "0x93146d9978d286ee085ba68ee1786a0b6eda64ec",
    "tier": 3,
    "prizeIndex": 6,
    "claimed": true,
    "amount": "842182760480281660",
    "userTwab": "29991000999950000980003",
    "totalSupplyTwab": "29997154476824741259698",
    "isTimeRangeSafe": {
      "isTimeRangeSafe": true,
      "isTimeRangeSafeStartTimePlusOne": true
    }
  },
  {
    "vault": "0x80f5984ad748878c9822af1231deef7466ad85bf",
    "winner": "0x93146d9978d286ee085ba68ee1786a0b6eda64ec",
    "tier": 3,
    "prizeIndex": 16,
    "claimed": true,
    "amount": "842182760480281660",
    "userTwab": "29991000999950000980003",
    "totalSupplyTwab": "29997154476824741259698",
    "isTimeRangeSafe": {
      "isTimeRangeSafe": true,
      "isTimeRangeSafeStartTimePlusOne": true
    }
  },
  {
    "vault": "0x80f5984ad748878c9822af1231deef7466ad85bf",
    "winner": "0x93146d9978d286ee085ba68ee1786a0b6eda64ec",
    "tier": 3,
    "prizeIndex": 60,
    "claimed": true,
    "amount": "842182760480281660",
    "userTwab": "29991000999950000980003",
    "totalSupplyTwab": "29997154476824741259698",
    "isTimeRangeSafe": {
      "isTimeRangeSafe": true,
      "isTimeRangeSafeStartTimePlusOne": true
    }
  },
  {
    "vault": "0x80f5984ad748878c9822af1231deef7466ad85bf",
    "winner": "0x93146d9978d286ee085ba68ee1786a0b6eda64ec",
    "tier": 4,
    "prizeIndex": 10,
    "claimed": true,
    "amount": "170056134327749182",
    "userTwab": "29991000999950000980003",
    "totalSupplyTwab": "29997154476824741259698",
    "isTimeRangeSafe": {
      "isTimeRangeSafe": true,
      "isTimeRangeSafeStartTimePlusOne": true
    }
  },
  {
    "vault": "0x80f5984ad748878c9822af1231deef7466ad85bf",
    "winner": "0x93146d9978d286ee085ba68ee1786a0b6eda64ec",
    "tier": 4,
    "prizeIndex": 12,
    "claimed": true,
    "amount": "170056134327749182",
    "userTwab": "29991000999950000980003",
    "totalSupplyTwab": "29997154476824741259698",
    "isTimeRangeSafe": {
      "isTimeRangeSafe": true,
      "isTimeRangeSafeStartTimePlusOne": true
    }
  },
  {
    "vault": "0x80f5984ad748878c9822af1231deef7466ad85bf",
    "winner": "0x93146d9978d286ee085ba68ee1786a0b6eda64ec",
    "tier": 4,
    "prizeIndex": 14,
    "claimed": true,
    "amount": "170056134327749182",
    "userTwab": "29991000999950000980003",
    "totalSupplyTwab": "29997154476824741259698",
    "isTimeRangeSafe": {
      "isTimeRangeSafe": true,
      "isTimeRangeSafeStartTimePlusOne": true
    }
  },
  {
    "vault": "0x80f5984ad748878c9822af1231deef7466ad85bf",
    "winner": "0x93146d9978d286ee085ba68ee1786a0b6eda64ec",
    "tier": 4,
    "prizeIndex": 16,
    "claimed": true,
    "amount": "170056134327749182",
    "userTwab": "29991000999950000980003",
    "totalSupplyTwab": "29997154476824741259698",
    "isTimeRangeSafe": {
      "isTimeRangeSafe": true,
      "isTimeRangeSafeStartTimePlusOne": true
    }
  },
  {
    "vault": "0x80f5984ad748878c9822af1231deef7466ad85bf",
    "winner": "0x93146d9978d286ee085ba68ee1786a0b6eda64ec",
    "tier": 4,
    "prizeIndex": 25,
    "claimed": true,
    "amount": "170056134327749182",
    "userTwab": "29991000999950000980003",
    "totalSupplyTwab": "29997154476824741259698",
    "isTimeRangeSafe": {
      "isTimeRangeSafe": true,
      "isTimeRangeSafeStartTimePlusOne": true
    }
  },
  {
    "vault": "0x80f5984ad748878c9822af1231deef7466ad85bf",
    "winner": "0x93146d9978d286ee085ba68ee1786a0b6eda64ec",
    "tier": 4,
    "prizeIndex": 30,
    "claimed": true,
    "amount": "170056134327749182",
    "userTwab": "29991000999950000980003",
    "totalSupplyTwab": "29997154476824741259698",
    "isTimeRangeSafe": {
      "isTimeRangeSafe": true,
      "isTimeRangeSafeStartTimePlusOne": true
    }
  }
]