[
  {
    "vault": "0x0771ba4b988c66afb02f9adf21f6e3a14d33c24e",
    "winner": "0x3714cf2183cfb4283e1c9daf5a3a253db292c30c",
    "tier": 3,
    "prizeIndex": 3,
    "claimed": false,
    "amount": "12255583901848998",
    "userTwab": "9996000599",
    "totalSupplyTwab": "387464880935",
    "isTimeRangeSafe": {
      "isTimeRangeSafe": true,
      "isTimeRangeSafeStartTimePlusOne": true
    }
  },
  {
    "vault": "0x0771ba4b988c66afb02f9adf21f6e3a14d33c24e",
    "winner": "0x93146d9978d286ee085ba68ee1786a0b6eda64ec",
    "tier": 0,
    "prizeIndex": 0,
    "claimed": false,
    "amount": "18394226664544770100",
    "userTwab": "167586199365",
    "totalSupplyTwab": "387464880935",
    "isTimeRangeSafe": {
      "isTimeRangeSafe": true,
      "isTimeRangeSafeStartTimePlusOne": true
    }
  },
  {
    "vault": "0x0771ba4b988c66afb02f9adf21f6e3a14d33c24e",
    "winner": "0x93146d9978d286ee085ba68ee1786a0b6eda64ec",
    "tier": 1,
    "prizeIndex": 0,
    "claimed": false,
    "amount": "1223423504772788683",
    "userTwab": "167586199365",
    "totalSupplyTwab": "387464880935",
    "isTimeRangeSafe": {
      "isTimeRangeSafe": true,
      "isTimeRangeSafeStartTimePlusOne": true
    }
  },
  {
    "vault": "0x0771ba4b988c66afb02f9adf21f6e3a14d33c24e",
    "winner": "0x93146d9978d286ee085ba68ee1786a0b6eda64ec",
    "tier": 2,
    "prizeIndex": 12,
    "claimed": false,
    "amount": "125398689181721637",
    "userTwab": "167586199365",
    "totalSupplyTwab": "387464880935",
    "isTimeRangeSafe": {
      "isTimeRangeSafe": true,
      "isTimeRangeSafeStartTimePlusOne": true
    }
  },
  {
    "vault": "0x0771ba4b988c66afb02f9adf21f6e3a14d33c24e",
    "winner": "0x93146d9978d286ee085ba68ee1786a0b6eda64ec",
    "tier": 3,
    "prizeIndex": 3,
    "claimed": false,
    "amount": "12255583901848998",
    "userTwab": "167586199365",
    "totalSupplyTwab": "387464880935",
    "isTimeRangeSafe": {
      "isTimeRangeSafe": true,
      "isTimeRangeSafeStartTimePlusOne": true
    }
  },
  {
    "vault": "0x8faf98698e4ff29149a8a9d06db20e3509f3754b",
    "winner": "0x2e18b4bcea9c25e88385cb7a567280c714f70b09",
    "tier": 2,
    "prizeIndex": 7,
    "claimed": false,
    "amount": "125398689181721637",
    "userTwab": "999900",
    "totalSupplyTwab": "14996398",
    "isTimeRangeSafe": {
      "isTimeRangeSafe": true,
      "isTimeRangeSafeStartTimePlusOne": true
    }
  },
  {
    "vault": "0x8faf98698e4ff29149a8a9d06db20e3509f3754b",
    "winner": "0x3994537274f3ff3eefc413e0d669b05d6446d46b",
    "tier": 2,
    "prizeIndex": 13,
    "claimed": false,
    "amount": "125398689181721637",
    "userTwab": "998700",
    "totalSupplyTwab": "14996398",
    "isTimeRangeSafe": {
      "isTimeRangeSafe": true,
      "isTimeRangeSafeStartTimePlusOne": true
    }
  },
  {
    "vault": "0x8faf98698e4ff29149a8a9d06db20e3509f3754b",
    "winner": "0x532e5508fe6a0288e247158bee9944e0ae3285d4",
    "tier": 2,
    "prizeIndex": 4,
    "claimed": false,
    "amount": "125398689181721637",
    "userTwab": "999200",
    "totalSupplyTwab": "14996398",
    "isTimeRangeSafe": {
      "isTimeRangeSafe": true,
      "isTimeRangeSafeStartTimePlusOne": true
    }
  },
  {
    "vault": "0x8faf98698e4ff29149a8a9d06db20e3509f3754b",
    "winner": "0x588cf9a1923369ed48ff14fd9d51210df8c031dc",
    "tier": 2,
    "prizeIndex": 6,
    "claimed": false,
    "amount": "125398689181721637",
    "userTwab": "999800",
    "totalSupplyTwab": "14996398",
    "isTimeRangeSafe": {
      "isTimeRangeSafe": true,
      "isTimeRangeSafeStartTimePlusOne": true
    }
  },
  {
    "vault": "0x8faf98698e4ff29149a8a9d06db20e3509f3754b",
    "winner": "0x588cf9a1923369ed48ff14fd9d51210df8c031dc",
    "tier": 2,
    "prizeIndex": 11,
    "claimed": false,
    "amount": "125398689181721637",
    "userTwab": "999800",
    "totalSupplyTwab": "14996398",
    "isTimeRangeSafe": {
      "isTimeRangeSafe": true,
      "isTimeRangeSafeStartTimePlusOne": true
    }
  },
  {
    "vault": "0x8faf98698e4ff29149a8a9d06db20e3509f3754b",
    "winner": "0x93146d9978d286ee085ba68ee1786a0b6eda64ec",
    "tier": 3,
    "prizeIndex": 4,
    "claimed": false,
    "amount": "12255583901848998",
    "userTwab": "998600",
    "totalSupplyTwab": "14996398",
    "isTimeRangeSafe": {
      "isTimeRangeSafe": true,
      "isTimeRangeSafeStartTimePlusOne": true
    }
  },
  {
    "vault": "0x8faf98698e4ff29149a8a9d06db20e3509f3754b",
    "winner": "0x9bd85eafd1972bcc70730b5429c21abf4254f355",
    "tier": 2,
    "prizeIndex": 9,
    "claimed": false,
    "amount": "125398689181721637",
    "userTwab": "999400",
    "totalSupplyTwab": "14996398",
    "isTimeRangeSafe": {
      "isTimeRangeSafe": true,
      "isTimeRangeSafeStartTimePlusOne": true
    }
  },
  {
    "vault": "0x8faf98698e4ff29149a8a9d06db20e3509f3754b",
    "winner": "0xd43e5593b938ba89c381da3418b36346b3c50956",
    "tier": 2,
    "prizeIndex": 6,
    "claimed": false,
    "amount": "125398689181721637",
    "userTwab": "998900",
    "totalSupplyTwab": "14996398",
    "isTimeRangeSafe": {
      "isTimeRangeSafe": true,
      "isTimeRangeSafeStartTimePlusOne": true
    }
  },
  {
    "vault": "0x8faf98698e4ff29149a8a9d06db20e3509f3754b",
    "winner": "0xfc1bc320b93cd1111b3e7d7139fb41f595ea3ece",
    "tier": 2,
    "prizeIndex": 7,
    "claimed": false,
    "amount": "125398689181721637",
    "userTwab": "1000000",
    "totalSupplyTwab": "14996398",
    "isTimeRangeSafe": {
      "isTimeRangeSafe": true,
      "isTimeRangeSafeStartTimePlusOne": true
    }
  }
]